qr_monkey/__init__.py
qr_monkey/qr_monkey.py
qr_monkey-0.1.0.dist-info/LICENSE
qr_monkey-0.1.0.dist-info/METADATA
qr_monkey-0.1.0.dist-info/WHEEL
qr_monkey-0.1.0.dist-info/RECORD
