Metadata-Version: 2.1
Name: qr_monkey
Version: 0.1.0
Summary: An API Client for qrcode-monkey API that integrates custom and unique looking QR codes into your system or workflow.
License: MIT
Author: Vansh Murad Kalia
Requires-Python: >=3.9,<4.0
Classifier: License :: OSI Approved :: MIT License
Classifier: Programming Language :: Python :: 3
Classifier: Programming Language :: Python :: 3.9
Classifier: Programming Language :: Python :: 3.10
Classifier: Programming Language :: Python :: 3.11
Classifier: Programming Language :: Python :: 3.12
